django_tree/__init__.py
django_tree/models.py
django_tree/migrations/__init__.py
django_orderable_tree-0.1.0.dist-info/LICENSE
django_orderable_tree-0.1.0.dist-info/METADATA
django_orderable_tree-0.1.0.dist-info/WHEEL
django_orderable_tree-0.1.0.dist-info/top_level.txt
django_orderable_tree-0.1.0.dist-info/RECORD
