Metadata-Version: 2.1
Name: django-orderable-tree
Version: 0.1.0
Summary: Tree structure for hierarchical data
Author-email: Vitaly Budovski <vbudovski@gmail.com>
License: Apache License
Project-URL: homepage, https://github.com/vbudovski/django-tree
Keywords: tree,database,hierarchical
Classifier: Development Status :: 3 - Alpha
Classifier: Environment :: Web Environment
Classifier: Framework :: Django
Classifier: Intended Audience :: Developers
Classifier: License :: OSI Approved :: Apache Software License
Classifier: Operating System :: OS Independent
Classifier: Programming Language :: Python
Classifier: Programming Language :: Python :: 3
Classifier: Topic :: Utilities
Requires-Python: >=3.8
License-File: LICENSE
Requires-Dist: django (>=3.2)
Provides-Extra: dev
Requires-Dist: isort ; extra == 'dev'
Requires-Dist: flake8 ; extra == 'dev'
Requires-Dist: pytest ; extra == 'dev'
Requires-Dist: pytest-django ; extra == 'dev'
Requires-Dist: pytest-cov ; extra == 'dev'
Requires-Dist: psycopg2 ; extra == 'dev'
